localc/__init__.py
localc/__main__.py
localc/errors.py
localc/node.py
localc/operators.py
localc/parser.py
localc/proposition.py
localc/scanner.py
localc-1.2.4.dist-info/LICENSE
localc-1.2.4.dist-info/METADATA
localc-1.2.4.dist-info/WHEEL
localc-1.2.4.dist-info/top_level.txt
localc-1.2.4.dist-info/RECORD
