Metadata-Version: 2.1
Name: localc
Version: 1.2.4
Summary: A simple logic calculator
Author-email: rankrev <307532500@qq.com>
License: MIT License
Project-URL: Homepage, https://gitee.com/rankrev/localc
Project-URL: Bug Tracker, https://gitee.com/rankrev/localc/issues
License-File: LICENSE
Requires-Dist: prettytable
Requires-Dist: ipython
